software_patterns/__init__.py
software_patterns/memoize.py
software_patterns/notification.py
software_patterns/proxy.py
software_patterns/py.typed
software_patterns/singleton.py
software_patterns/subclass_registry.py
software_patterns-2.0.1.dist-info/METADATA
software_patterns-2.0.1.dist-info/WHEEL
software_patterns-2.0.1.dist-info/licenses/LICENSE
software_patterns-2.0.1.dist-info/RECORD
