Metadata-Version: 2.4
Name: software_patterns
Version: 2.0.1
Summary: Software Design Patterns with types in Python.
License: AGPL-3.0-only
License-File: LICENSE
Keywords: software design patterns,design patterns,software patterns,python library
Author: Konstantinos Lampridis
Author-email: k.lampridis@hotmail.com
Maintainer: Konstantinos Lampridis
Maintainer-email: k.lampridis@hotmail.com
Requires-Python: >=3.6,<3.13
Classifier: Development Status :: 5 - Production/Stable
Classifier: Intended Audience :: Developers
Classifier: Intended Audience :: End Users/Desktop
Classifier: Intended Audience :: Science/Research
Classifier: License :: OSI Approved :: GNU Affero General Public License v3
Classifier: Natural Language :: English
Classifier: Operating System :: Unix
Classifier: Programming Language :: Python
Classifier: Programming Language :: Python :: 3
Classifier: Programming Language :: Python :: 3.6
Classifier: Programming Language :: Python :: 3.7
Classifier: Programming Language :: Python :: 3.8
Classifier: Programming Language :: Python :: 3.9
Classifier: Programming Language :: Python :: 3.10
Classifier: Programming Language :: Python :: 3.11
Classifier: Programming Language :: Python :: 3.12
Classifier: Programming Language :: Python :: 3 :: Only
Classifier: Topic :: Documentation :: Sphinx
Classifier: Topic :: Scientific/Engineering
Classifier: Topic :: Software Development
Classifier: Topic :: Software Development :: Libraries :: Python Modules
Classifier: Topic :: System :: Software Distribution
Classifier: Topic :: Utilities
Classifier: Typing :: Typed
Provides-Extra: docs
Provides-Extra: test
Requires-Dist: furo (>=2021.08.31,<2022.0.0) ; (python_version >= "3.8") and (extra == "docs")
Requires-Dist: pytest (>=9.0.0,<10.0.0) ; (python_version >= "3.10" and python_version < "3.13") and (extra == "test")
Requires-Dist: pytest-cov (>=7.0.0,<8.0.0) ; (python_version >= "3.10" and python_version < "3.13") and (extra == "test")
Requires-Dist: sphinx (>=4.0,<5.0) ; (python_version >= "3.8") and (extra == "docs")
Requires-Dist: sphinx-argparse-cli (>=1.5,<2.0.0) ; (python_version >= "3.8") and (extra == "docs")
Requires-Dist: sphinx-autodoc-typehints (>=1.10,<2.0.0) ; (python_version >= "3.8") and (extra == "docs")
Requires-Dist: sphinx-rtd-theme (==0.5.0) ; (python_version >= "3.8") and (extra == "docs")
Requires-Dist: sphinxcontrib-spelling (==7.6.2) ; (python_version >= "3.8") and (extra == "docs")
